genetic_tree/genetic_tree.py
genetic_tree/__init__.py
genetic_tree/genetic/crosser.py
genetic_tree/genetic/mutator.py
genetic_tree/genetic/stopper.py
genetic_tree/genetic/initializer.py
genetic_tree/genetic/evaluator.py
genetic_tree/genetic/selector.py
genetic_tree/genetic/__init__.py
genetic_tree/tree/tree.cpython-36m-x86_64-linux-gnu.so
genetic_tree/tree/builder.cpython-36m-x86_64-linux-gnu.so
genetic_tree/tree/mutator.cpython-36m-x86_64-linux-gnu.so
genetic_tree/tree/evaluation.cpython-36m-x86_64-linux-gnu.so
genetic_tree/tree/crosser.cpython-36m-x86_64-linux-gnu.so
genetic_tree/tree/_utils.cpython-36m-x86_64-linux-gnu.so
genetic_tree/tree/observations.cpython-36m-x86_64-linux-gnu.so
genetic_tree/tree/__init__.py
genetic_tree/tree/thresholds.cpython-36m-x86_64-linux-gnu.so
genetic_tree-0.1.2.dist-info/top_level.txt
genetic_tree-0.1.2.dist-info/RECORD
genetic_tree-0.1.2.dist-info/METADATA
genetic_tree-0.1.2.dist-info/LICENSE
genetic_tree-0.1.2.dist-info/WHEEL
quality_tests/quality_tester.py
quality_tests/methods.py
quality_tests/json_plot.py
quality_tests/__init__.py
tests/test_tree.py
tests/utils_testing.py
tests/test_mutator.py
tests/test_selector.py
tests/test_threading.py
tests/test_stop.py
tests/test_genetic.py
tests/test_genetic_tree.py
tests/test_evaluator.py
tests/test_prediction.py
tests/test_crosser.py
tests/test_initalization.py
tests/test_observations.py
tests/__init__.py
tests/test_thresholds.py
tests/test_copying.py
tests/test_memory.py
