Metadata-Version: 2.1
Name: genetic-tree
Version: 0.1.2
Summary: Constructing decision trees with genetic algorithm with a scikit-learn inspired API
Home-page: https://github.com/pysiakk/GeneticTree
Author: Tomasz Makowski & Karol Pysiak
Author-email: tomasz.tu.tm@gmail.com
License: UNKNOWN
Platform: UNKNOWN
Requires-Python: >=3.6
Requires-Dist: aenum (>=2.2.4)
Requires-Dist: numpy (>=1.19.2)
Requires-Dist: scipy (>=1.5.2)
